betagen/__init__.py
betagen/__version__.py
betagen/_version.py
betagen/utils.py
betagen-1.0.7.dist-info/LICENSE
betagen-1.0.7.dist-info/METADATA
betagen-1.0.7.dist-info/WHEEL
betagen-1.0.7.dist-info/top_level.txt
betagen-1.0.7.dist-info/RECORD
